xarm/__init__.py
xarm/controller.py
xarm/servo.py
xarm/util.py
xarm-0.0.4.dist-info/LICENSE
xarm-0.0.4.dist-info/METADATA
xarm-0.0.4.dist-info/WHEEL
xarm-0.0.4.dist-info/top_level.txt
xarm-0.0.4.dist-info/RECORD
