Metadata-Version: 2.1
Name: xarm
Version: 0.0.4
Summary: Servo controller to manipulate xArm and LeArm
Home-page: https://github.com/ccourson/xArmServoController
Author: Chris Courson
Author-email: chris@chrisbot.com
License: UNKNOWN
Project-URL: Bug Tracker, https://github.com/ccourson/xArmServoController/issues
Platform: UNKNOWN
Classifier: Programming Language :: Python :: 3
Classifier: License :: OSI Approved :: MIT License
Classifier: Operating System :: OS Independent
Requires-Python: >=3.6
